{
	"interstitial_enable":true,
	"new_items": ["Stickers pésimos para WhatsApp"],
	"items": [{
		"app_name": "Memes frases Stickers",
		"google_play_id": "com.sensei.ligar",
		"url_icon": "ic_memes.png",
		"id": 1,
		"order": 10,
		"active": true,
		"show_banner": false,
		"banner_image": "banner_memesanimated2020stickers.jpg",
		"bannners_to_show": []

	},{
		"app_name": "Music Stickers",
		"google_play_id": "com.pordio.musiclegends",
		"url_icon": "ic_music.png",
		"id": 2,
		"order": 20,
		"active": true,
		"show_banner": false,
		"banner_image": "",
		"bannners_to_show": []

	}, {
		"app_name": "Stickers de Boca Juniors",
		"google_play_id": "com.pordio.boca",
		"url_icon": "ic_boca.png",
		"id": 3,
		"order": 30,
		"active": true,
		"show_banner": true,
		"banner_image": "",
		"bannners_to_show": [1,5]
	}, {
		"app_name": "Stickers pésimos para WhatsApp",
		"google_play_id": "ic_pesimo",
		"url_icon": "ic_food.png",
		"id": 4,
		"order": 40,
		"active": true,
		"show_banner": false,
		"banner_image": "",
		"bannners_to_show": []
	}, {
		"app_name": "Stickers de eventos y fiestas",
		"google_play_id": "com.pordio.festejos",
		"url_icon": "ic_festejos.png",
		"id": 5,
		"order": 50,
		"active": true,
		"show_banner": false,
		"banner_image": "banner_loveanimated2020.jpg",
		"bannners_to_show": []
	}]
}